[
    {
      "employeeID": "12345",
      "name": "Rajesh Kumar Singh",
      "gender": "Male",
      "phone": "9876543210",
      "email": "rajesh.singh@pwd.gov.in",
      "department": "Public Works Department (PWD)",
      "status": "Not Assigned",
      "reportID": ""
    },
    {
      "employeeID": "23456",
      "name": "Priya Sharma",
      "gender": "Female",
      "phone": "9876543211",
      "email": "priya.sharma@wsb.gov.in",
      "department": "Water Supply & Sewerage Board",
      "status": "Not Assigned",
      "reportID": ""
    },
    {
      "employeeID": "34567",
      "name": "Amit Patel",
      "gender": "Male",
      "phone": "9876543212",
      "email": "amit.patel@eb.gov.in",
      "department": "Electricity Board",
      "status": "Not Assigned",
      "reportID": ""
    },
    {
      "employeeID": "45678",
      "name": "Sunil Verma",
      "gender": "Male",
      "phone": "9876543213",
      "email": "sunil.verma@pcb.gov.in",
      "department": "Pollution Control Board / Environment Department",
      "status": "Not Assigned",
      "reportID": ""
    },
    {
      "employeeID": "56789",
      "name": "Vikram Joshi",
      "gender": "Male",
      "phone": "9876543214",
      "email": "vikram.joshi@mc.gov.in",
      "department": "Municipal Corporation (Sanitation Wing)",
      "status": "Not Assigned",
      "reportID": ""
    },
    {
      "employeeID": "67890",
      "name": "Anil Gupta",
      "gender": "Male",
      "phone": "9876543215",
      "email": "anil.gupta@uda.gov.in",
      "department": "Urban Development Authority / PWD",
      "status": "Not Assigned",
      "reportID": ""
    },
    {
      "employeeID": "78901",
      "name": "Suresh Yadav",
      "gender": "Male",
      "phone": "9876543216",
      "email": "suresh.yadav@pwd.gov.in",
      "department": "Public Works Department (PWD)",
      "status": "Not Assigned",
      "reportID": ""
    },
    {
      "employeeID": "89012",
      "name": "Karan Mishra",
      "gender": "Male",
      "phone": "9876543217",
      "email": "karan.mishra@wsb.gov.in",
      "department": "Water Supply & Sewerage Board",
      "status": "Not Assigned",
      "reportID": ""
    },
    {
      "employeeID": "90123",
      "name": "Deepak Agarwal",
      "gender": "Male",
      "phone": "9876543218",
      "email": "deepak.agarwal@eb.gov.in",
      "department": "Electricity Board",
      "status": "Not Assigned",
      "reportID": ""
    },
    {
      "employeeID": "01234",
      "name": "Meera Reddy",
      "gender": "Female",
      "phone": "9876543219",
      "email": "meera.reddy@pcb.gov.in",
      "department": "Pollution Control Board / Environment Department",
      "status": "Not Assigned",
      "reportID": ""
    },
    {
      "employeeID": "12340",
      "name": "Ravi Chandra",
      "gender": "Male",
      "phone": "9876543220",
      "email": "ravi.chandra@mc.gov.in",
      "department": "Municipal Corporation (Sanitation Wing)",
      "status": "Not Assigned",
      "reportID": ""
    },
    {
      "employeeID": "23451",
      "name": "Pooja Nair",
      "gender": "Female",
      "phone": "9876543221",
      "email": "pooja.nair@uda.gov.in",
      "department": "Urban Development Authority / PWD",
      "status": "Not Assigned",
      "reportID": ""
    },
    {
      "employeeID": "34562",
      "name": "Manoj Tiwari",
      "gender": "Male",
      "phone": "9876543222",
      "email": "manoj.tiwari@pwd.gov.in",
      "department": "Public Works Department (PWD)",
      "status": "Not Assigned",
      "reportID": ""
    },
    {
      "employeeID": "45673",
      "name": "Rashmi Sinha",
      "gender": "Female",
      "phone": "9876543223",
      "email": "rashmi.sinha@wsb.gov.in",
      "department": "Water Supply & Sewerage Board",
      "status": "Not Assigned",
      "reportID": ""
    },
    {
      "employeeID": "56784",
      "name": "Ajay Khanna",
      "gender": "Male",
      "phone": "9876543224",
      "email": "ajay.khanna@eb.gov.in",
      "department": "Electricity Board",
      "status": "Not Assigned",
      "reportID": ""
    },
    {
      "employeeID": "67895",
      "name": "Neha Kapoor",
      "gender": "Female",
      "phone": "9876543225",
      "email": "neha.kapoor@pcb.gov.in",
      "department": "Pollution Control Board / Environment Department",
      "status": "Not Assigned",
      "reportID": ""
    },
    {
      "employeeID": "78906",
      "name": "Sanjay Pandey",
      "gender": "Male",
      "phone": "9876543226",
      "email": "sanjay.pandey@mc.gov.in",
      "department": "Municipal Corporation (Sanitation Wing)",
      "status": "Not Assigned",
      "reportID": ""
    },
    {
      "employeeID": "89017",
      "name": "Divya Jain",
      "gender": "Female",
      "phone": "9876543227",
      "email": "divya.jain@uda.gov.in",
      "department": "Urban Development Authority / PWD",
      "status": "Not Assigned",
      "reportID": ""
    },
    {
      "employeeID": "90128",
      "name": "Kiran Malhotra",
      "gender": "Male",
      "phone": "9876543228",
      "email": "kiran.malhotra@pwd.gov.in",
      "department": "Public Works Department (PWD)",
      "status": "Not Assigned",
      "reportID": ""
    },
    {
      "employeeID": "01239",
      "name": "Seema Ghosh",
      "gender": "Female",
      "phone": "9876543229",
      "email": "seema.ghosh@wsb.gov.in",
      "department": "Water Supply & Sewerage Board",
      "status": "Not Assigned",
      "reportID": ""
    },
    {
      "employeeID": "12347",
      "name": "Rohit Bansal",
      "gender": "Male",
      "phone": "9876543230",
      "email": "rohit.bansal@eb.gov.in",
      "department": "Electricity Board",
      "status": "Not Assigned",
      "reportID": ""
    },
    {
      "employeeID": "23458",
      "name": "Shweta Kulkarni",
      "gender": "Female",
      "phone": "9876543231",
      "email": "shweta.kulkarni@pcb.gov.in",
      "department": "Pollution Control Board / Environment Department",
      "status": "Not Assigned",
      "reportID": ""
    },
    {
      "employeeID": "34569",
      "name": "Arjun Desai",
      "gender": "Male",
      "phone": "9876543232",
      "email": "arjun.desai@mc.gov.in",
      "department": "Municipal Corporation (Sanitation Wing)",
      "status": "Not Assigned",
      "reportID": ""
    },
    {
      "employeeID": "45680",
      "name": "Rekha Bhatt",
      "gender": "Female",
      "phone": "9876543233",
      "email": "rekha.bhatt@uda.gov.in",
      "department": "Urban Development Authority / PWD",
      "status": "Not Assigned",
      "reportID": ""
    },
    {
      "employeeID": "56791",
      "name": "Naveen Thakur",
      "gender": "Male",
      "phone": "9876543234",
      "email": "naveen.thakur@pwd.gov.in",
      "department": "Public Works Department (PWD)",
      "status": "Not Assigned",
      "reportID": ""
    },
    {
      "employeeID": "67802",
      "name": "Geeta Saxena",
      "gender": "Female",
      "phone": "9876543235",
      "email": "geeta.saxena@wsb.gov.in",
      "department": "Water Supply & Sewerage Board",
      "status": "Not Assigned",
      "reportID": ""
    },
    {
      "employeeID": "78913",
      "name": "Ashish Mehta",
      "gender": "Male",
      "phone": "9876543236",
      "email": "ashish.mehta@eb.gov.in",
      "department": "Electricity Board",
      "status": "Not Assigned",
      "reportID": ""
    },
    {
      "employeeID": "89024",
      "name": "Usha Tripathi",
      "gender": "Female",
      "phone": "9876543237",
      "email": "usha.tripathi@pcb.gov.in",
      "department": "Pollution Control Board / Environment Department",
      "status": "Not Assigned",
      "reportID": ""
    },
    {
      "employeeID": "90135",
      "name": "Pramod Kumar",
      "gender": "Male",
      "phone": "9876543238",
      "email": "pramod.kumar@mc.gov.in",
      "department": "Municipal Corporation (Sanitation Wing)",
      "status": "Not Assigned",
      "reportID": ""
    },
    {
      "employeeID": "01246",
      "name": "Nidhi Aggarwal",
      "gender": "Female",
      "phone": "9876543239",
      "email": "nidhi.aggarwal@uda.gov.in",
      "department": "Urban Development Authority / PWD",
      "status": "Not Assigned",
      "reportID": ""
    },
    {
      "employeeID": "12357",
      "name": "Harish Bhatia",
      "gender": "Male",
      "phone": "9876543240",
      "email": "harish.bhatia@pwd.gov.in",
      "department": "Public Works Department (PWD)",
      "status": "Not Assigned",
      "reportID": ""
    },
    {
      "employeeID": "23468",
      "name": "Mamta Rao",
      "gender": "Female",
      "phone": "9876543241",
      "email": "mamta.rao@wsb.gov.in",
      "department": "Water Supply & Sewerage Board",
      "status": "Not Assigned",
      "reportID": ""
    },
    {
      "employeeID": "34579",
      "name": "Bhushan Patil",
      "gender": "Male",
      "phone": "9876543242",
      "email": "bhushan.patil@eb.gov.in",
      "department": "Electricity Board",
      "status": "Not Assigned",
      "reportID": ""
    },
    {
      "employeeID": "45691",
      "name": "Vandana Srivastava",
      "gender": "Female",
      "phone": "9876543243",
      "email": "vandana.srivastava@pcb.gov.in",
      "department": "Pollution Control Board / Environment Department",
      "status": "Not Assigned",
      "reportID": ""
    },
    {
      "employeeID": "56802",
      "name": "Manish Chauhan",
      "gender": "Male",
      "phone": "9876543244",
      "email": "manish.chauhan@mc.gov.in",
      "department": "Municipal Corporation (Sanitation Wing)",
      "status": "Not Assigned",
      "reportID": ""
    },
    {
      "employeeID": "67913",
      "name": "Preeti Devi",
      "gender": "Female",
      "phone": "9876543245",
      "email": "preeti.devi@uda.gov.in",
      "department": "Urban Development Authority / PWD",
      "status": "Not Assigned",
      "reportID": ""
    },
    {
      "employeeID": "78024",
      "name": "Dinesh Gupta",
      "gender": "Male",
      "phone": "9876543246",
      "email": "dinesh.gupta@pwd.gov.in",
      "department": "Public Works Department (PWD)",
      "status": "Not Assigned",
      "reportID": ""
    },
    {
      "employeeID": "89135",
      "name": "Swati Kohli",
      "gender": "Female",
      "phone": "9876543247",
      "email": "swati.kohli@wsb.gov.in",
      "department": "Water Supply & Sewerage Board",
      "status": "Not Assigned",
      "reportID": ""
    },
    {
      "employeeID": "90246",
      "name": "Raman Sharma",
      "gender": "Male",
      "phone": "9876543248",
      "email": "raman.sharma@eb.gov.in",
      "department": "Electricity Board",
      "status": "Not Assigned",
      "reportID": ""
    },
    {
      "employeeID": "01357",
      "name": "Anjali Chaudhary",
      "gender": "Female",
      "phone": "9876543249",
      "email": "anjali.chaudhary@pcb.gov.in",
      "department": "Pollution Control Board / Environment Department",
      "status": "Not Assigned",
      "reportID": ""
    },
    {
      "employeeID": "12468",
      "name": "Yogesh Arora",
      "gender": "Male",
      "phone": "9876543250",
      "email": "yogesh.arora@mc.gov.in",
      "department": "Municipal Corporation (Sanitation Wing)",
      "status": "Not Assigned",
      "reportID": ""
    },
    {
      "employeeID": "23579",
      "name": "Smita Dubey",
      "gender": "Female",
      "phone": "9876543251",
      "email": "smita.dubey@uda.gov.in",
      "department": "Urban Development Authority / PWD",
      "status": "Not Assigned",
      "reportID": ""
    },
    {
      "employeeID": "34680",
      "name": "Rakesh Jha",
      "gender": "Male",
      "phone": "9876543252",
      "email": "rakesh.jha@pwd.gov.in",
      "department": "Public Works Department (PWD)",
      "status": "Not Assigned",
      "reportID": ""
    },
    {
      "employeeID": "45791",
      "name": "Sunita Saini",
      "gender": "Female",
      "phone": "9876543253",
      "email": "sunita.saini@wsb.gov.in",
      "department": "Water Supply & Sewerage Board",
      "status": "Not Assigned",
      "reportID": ""
    },
    {
      "employeeID": "56802",
      "name": "Vinod Rawat",
      "gender": "Male",
      "phone": "9876543254",
      "email": "vinod.rawat@eb.gov.in",
      "department": "Electricity Board",
      "status": "Not Assigned",
      "reportID": ""
    }
  ]